django_mailformer-0.0.1.data/data/HISTORY.rst
django_mailformer-0.0.1.data/data/README.rst
django_mailformer-0.0.1.dist-info/DESCRIPTION.rst
django_mailformer-0.0.1.dist-info/METADATA
django_mailformer-0.0.1.dist-info/RECORD
django_mailformer-0.0.1.dist-info/WHEEL
django_mailformer-0.0.1.dist-info/metadata.json
django_mailformer-0.0.1.dist-info/top_level.txt
mailformer/__init__.py
mailformer/admin.py
mailformer/admin_pseudo_fields.py
mailformer/apps.py
mailformer/constants.py
mailformer/forms.py
mailformer/models.py
mailformer/models_tools.py
mailformer/processor.py
mailformer/tools.py
mailformer/urls.py
mailformer/views.py
mailformer/views_mixin.py
mailformer/management/__init__.py
mailformer/management/commands/__init__.py
mailformer/management/commands/mailformer_new.py
mailformer/management/commands/mailformer_purge.py
mailformer/management/commands/mailformer_retry.py
mailformer/migrations/0001_initial.py
mailformer/migrations/__init__.py
mailformer/signals/__init__.py
mailformer/signals/listeners.py
mailformer/templatetags/__init__.py
mailformer/templatetags/mailformer.py
