Metadata-Version: 2.0
Name: django-mailformer
Version: 0.0.1
Summary: Django Mailformer
Home-page: https://github.com/developersociety/django-mailformer
Author: The Developer Society
Author-email: studio@dev.ngo
License: BSD license
Keywords: django glitter
Platform: UNKNOWN
Classifier: Development Status :: 4 - Beta
Classifier: Intended Audience :: Developers
Classifier: License :: OSI Approved :: BSD License
Classifier: Natural Language :: English
Classifier: Programming Language :: Python :: 3.5
Requires-Python: >=3.5
Requires-Dist: Django (>=1.8.18)
